clinicedc_utils/__init__.py
clinicedc_utils/constants.py
clinicedc_utils/convert_units/__init__.py
clinicedc_utils/convert_units/convert_units.py
clinicedc_utils/convert_units/micromoles_per_liter_to.py
clinicedc_utils/convert_units/milligrams_per_deciliter_to.py
clinicedc_utils/convert_units/units_converter.py
clinicedc_utils/dataframe/__init__.py
clinicedc_utils/dataframe/coerce_date_columns.py
clinicedc_utils/dataframe/convert_and_clean_string_columns.py
clinicedc_utils/dataframe/convert_numeric_columns.py
clinicedc_utils/dataframe/convert_visit_code_to_float.py
clinicedc_utils/egfr_calculators/__init__.py
clinicedc_utils/egfr_calculators/base_egfr.py
clinicedc_utils/egfr_calculators/egfr_ckd_epi2009.py
clinicedc_utils/egfr_calculators/egfr_ckd_epi_2021.py
clinicedc_utils/egfr_calculators/egfr_cockcroft_gault.py
clinicedc_utils/egfr_calculators/egfr_percent_change.py
clinicedc_utils/exceptions.py
clinicedc_utils/export_raw_tables/__init__.py
clinicedc_utils/export_raw_tables/export_raw_tables.py
clinicedc_utils/export_raw_tables/get_df_subject_consent.py
clinicedc_utils/export_raw_tables/get_df_subject_visit.py
clinicedc_utils/export_raw_tables/merge_with_subject_consent.py
clinicedc_utils/export_raw_tables/merge_with_subject_visit.py
clinicedc_utils/misc/__init__.py
clinicedc_utils/misc/get_display_from_choices.py
clinicedc_utils/round_up/__init__.py
clinicedc_utils/round_up/round_half_away_from_zero.py
clinicedc_utils/round_up/round_half_up.py
clinicedc_utils/round_up/round_up.py
clinicedc_utils-1.0.2.dist-info/WHEEL
clinicedc_utils-1.0.2.dist-info/METADATA
clinicedc_utils-1.0.2.dist-info/RECORD
