Metadata-Version: 2.3
Name: clinicedc-utils
Version: 1.0.2
Summary: Add your description here
Author: Erik van Widenfelt
Author-email: Erik van Widenfelt <ew2789@gmail.com>
Classifier: Development Status :: 5 - Production/Stable
Classifier: Environment :: Web Environment
Classifier: Framework :: Django
Classifier: Framework :: Django :: 5.2
Classifier: Development Status :: 5 - Production/Stable
Classifier: Intended Audience :: Developers
Classifier: Intended Audience :: Science/Research
Classifier: Operating System :: OS Independent
Classifier: Programming Language :: Python :: 3.10
Classifier: Programming Language :: Python :: 3.11
Classifier: Programming Language :: Python :: 3.12
Classifier: Programming Language :: Python :: 3.13
Requires-Dist: clinicedc-constants>=1.0.1
Requires-Dist: pandas>=2.3.3
Requires-Dist: remote-read-sql>=1.2.3
Requires-Dist: sqlalchemy>=2.0.44
Requires-Dist: tqdm>=4.67.1
Maintainer: Erik van Widenfelt
Maintainer-email: Erik van Widenfelt <ew2789@gmail.com>
Requires-Python: >=3.11
Project-URL: Changelog, https://github.com/clinicedc/clinicedc-utils/blob/main/CHANGES
Project-URL: Documentation, https://github.com/clinicedc/clinicedc-utils/docs
Project-URL: Homepage, https://github.com/clinicedc/clinicedc-utils
Project-URL: Repository, https://github.com/clinicedc/eclinicedc-utils.git
